airdragon/__init__.py
airdragon/layouts.py
airdragon/py.typed
airdragon/tags.py
airdragon-0.4.0.dist-info/WHEEL
airdragon-0.4.0.dist-info/METADATA
airdragon-0.4.0.dist-info/RECORD
