Metadata-Version: 2.3
Name: AirDragon
Version: 0.4.0
Summary: Air + BasecoatUI + TailwindCSS made easy.
Author: Daniel Roy Greenfeld, Audrey Roy Greenfeld
Author-email: Daniel Roy Greenfeld <daniel@feldroy.com>, Audrey Roy Greenfeld <audrey@feldroy.com>
Requires-Dist: air[standard]>=0.41.1
Requires-Python: >=3.13
